code2mermaid/__init__.py
code2mermaid/converter.py
code2mermaid/core.py
code2mermaid/style.py
code2mermaid-0.3.0.dist-info/LICENSE
code2mermaid-0.3.0.dist-info/METADATA
code2mermaid-0.3.0.dist-info/WHEEL
code2mermaid-0.3.0.dist-info/top_level.txt
code2mermaid-0.3.0.dist-info/RECORD
