Metadata-Version: 2.1
Name: code2mermaid
Version: 0.3.0
Summary: Python code converter for Mermaid chartflows
Author-email: Vilson Rodrigues <vilsonrodrigues07@hotmail.com>
Maintainer-email: Vilson Rodrigues <vilsonrodrigues07@hotmail.com>
Project-URL: Homepage, https://github.com/vilsonrodrigues/code2mermaid
Project-URL: Bug Reports, https://github.com/vilsonrodrigues/code2mermaid/issues
Keywords: mermaid
Classifier: Intended Audience :: Developers
Classifier: Topic :: Software Development :: Build Tools
Classifier: License :: OSI Approved :: MIT License
Classifier: Programming Language :: Python :: 3
Classifier: Programming Language :: Python :: 3.8
Classifier: Programming Language :: Python :: 3.9
Classifier: Programming Language :: Python :: 3.10
Classifier: Programming Language :: Python :: 3.11
Classifier: Programming Language :: Python :: 3.12
Classifier: Programming Language :: Python :: 3.13
Classifier: Programming Language :: Python :: 3 :: Only
Requires-Python: >=3.8
License-File: LICENSE
